xxxchat/__init__.py
xxxchat/command/__init__.py
xxxchat/command/__main__.py
xxxchat/commons/__init__.py
xxxchat/commons/config.py
xxxchat/configuration/__init__.py
xxxchat/configuration/profile_config.py
xxxchat/utils/CommonUtil.py
xxxchat/utils/__init__.py
xxxchat/utils/logger.py
xxxchat/xxx/CommandChat.py
xxxchat/xxx/__init__.py
xxx_chat-0.0.4.dist-info/LICENSE
xxx_chat-0.0.4.dist-info/METADATA
xxx_chat-0.0.4.dist-info/WHEEL
xxx_chat-0.0.4.dist-info/entry_points.txt
xxx_chat-0.0.4.dist-info/top_level.txt
xxx_chat-0.0.4.dist-info/RECORD
