Metadata-Version: 2.1
Name: xxx-chat
Version: 0.0.4
Summary: use command to chat with openai models, for :bear:
Home-page: https://github.com/
Author: xoto
Author-email: xxx.tao.c@gmail.com
Classifier: Programming Language :: Python :: 3
Classifier: License :: OSI Approved :: MIT License
Classifier: Operating System :: OS Independent
License-File: LICENSE
Requires-Dist: click
